firebase_push/__init__.py
firebase_push/admin.py
firebase_push/apps.py
firebase_push/defaults.py
firebase_push/tasks.py
firebase_push/utils.py
firebase_push/conf/__init__.py
firebase_push/conf/settings.py
firebase_push/conf/urls.py
firebase_push/management/__init__.py
firebase_push/management/commands/__init__.py
firebase_push/management/commands/age_devices.py
firebase_push/management/commands/cleanup_devices.py
firebase_push/management/commands/cleanup_history.py
firebase_push/management/commands/test_push.py
firebase_push/message/__init__.py
firebase_push/message/base.py
firebase_push/message/localized_message.py
firebase_push/message/message.py
firebase_push/migrations/0001_initial.py
firebase_push/migrations/0002_default_topic.py
firebase_push/migrations/__init__.py
firebase_push/models/__init__.py
firebase_push/models/devices.py
firebase_push/models/history.py
firebase_push/models/topics.py
firebase_push/serializers/__init__.py
firebase_push/serializers/devices.py
firebase_push/serializers/topics.py
firebase_push/templates/firebase_push/send_push.html
firebase_push/views/__init__.py
firebase_push/views/device.py
firebase_push-0.2.10.dist-info/LICENSE
firebase_push-0.2.10.dist-info/WHEEL
firebase_push-0.2.10.dist-info/METADATA
firebase_push-0.2.10.dist-info/RECORD
