Metadata-Version: 2.1
Name: firebase_push
Version: 0.2.10
Summary: Firebase push notifications for Django, based on official SDK
Keywords: django,utils
Author-email: Johannes Schriewer <j.schriewer@anfe.ma>
Requires-Python: >=3.10
Classifier: License :: OSI Approved :: MIT License
Classifier: Framework :: Django
Classifier: Intended Audience :: Developers
Classifier: Programming Language :: Python :: 3
Classifier: Programming Language :: Python :: 3 :: Only
Classifier: Programming Language :: Python :: 3.10
Classifier: Programming Language :: Python :: 3.11
Classifier: Operating System :: OS Independent
Classifier: Topic :: Software Development :: Libraries
Requires-Dist: Django>=4.1
Requires-Dist: celery>=5.2
Requires-Dist: firebase-admin>=6.0
Requires-Dist: django-admin-extra-buttons
Requires-Dist: djangorestframework>=3.14.0
Requires-Dist: typing_extensions >= 4.1; python_version < '3.11'
Project-URL: Home, https://github.com/anfema/firebase_push
